synnax_lab_sdk/__init__.py
synnax_lab_sdk/client.py
synnax_lab_sdk/constants.py
synnax_lab_sdk/files_client.py
synnax_lab_sdk/py.typed
synnax_lab_sdk/api_clients/__init__.py
synnax_lab_sdk/api_clients/dataset.py
synnax_lab_sdk/api_clients/prediction_submission.py
synnax_lab_sdk/helpers/__init__.py
synnax_lab_sdk/helpers/timedelta.py
synnax_lab_sdk/http_client/__init__.py
synnax_lab_sdk/http_client/bearer_token.py
synnax_lab_sdk/http_client/errors.py
synnax_lab_sdk/http_client/http_client.py
synnax_lab_sdk/http_client/request.py
synnax_lab_sdk-2.1.0.dist-info/METADATA
synnax_lab_sdk-2.1.0.dist-info/WHEEL
synnax_lab_sdk-2.1.0.dist-info/RECORD
