Metadata-Version: 2.4
Name: synnax-lab-sdk
Version: 2.1.0
Summary: Synnax Lab SDK for downloading training data and uploading predictions
Project-URL: Homepage, https://synnax.ai
Keywords: synnax
Requires-Python: >=3.8
Requires-Dist: inflect
Requires-Dist: python-dateutil
Requires-Dist: requests
Requires-Dist: tqdm
Provides-Extra: all
Requires-Dist: black; extra == 'all'
Requires-Dist: mypy; extra == 'all'
Requires-Dist: types-python-dateutil; extra == 'all'
Requires-Dist: types-requests; extra == 'all'
Requires-Dist: types-tqdm; extra == 'all'
Provides-Extra: dev
Requires-Dist: black; extra == 'dev'
Requires-Dist: mypy; extra == 'dev'
Requires-Dist: types-python-dateutil; extra == 'dev'
Requires-Dist: types-requests; extra == 'dev'
Requires-Dist: types-tqdm; extra == 'dev'
